pyrosstsi/__init__.py
pyrosstsi/contactMatrix.cpython-37m-darwin.so
pyrosstsi/deterministic.cpython-37m-darwin.so
pyrosstsi/utils.cpython-37m-darwin.so
pyrosstsi-1.0.1.dist-info/LICENSE
pyrosstsi-1.0.1.dist-info/METADATA
pyrosstsi-1.0.1.dist-info/WHEEL
pyrosstsi-1.0.1.dist-info/top_level.txt
pyrosstsi-1.0.1.dist-info/RECORD
