Metadata-Version: 2.1
Name: pyrosstsi
Version: 1.0.1
Summary: python library for numerical simulation of infectious disease
Home-page: https://github.com/rajeshrinet/pyrosstsi
Author: The PyRossTSI team
Author-email: UNKNOWN
License: MIT
Platform: works on all platforms (such as LINUX
Platform: macOS
Platform: and Microsoft Windows)
Requires-Dist: cython
Requires-Dist: numpy
Requires-Dist: scipy
Requires-Dist: nlopt
